max7219/__init__.py
micropython_max7219-0.2.0.dist-info/LICENSE.txt
micropython_max7219-0.2.0.dist-info/METADATA
micropython_max7219-0.2.0.dist-info/WHEEL
micropython_max7219-0.2.0.dist-info/top_level.txt
micropython_max7219-0.2.0.dist-info/RECORD
