Metadata-Version: 2.1
Name: micropython-max7219
Version: 0.2.0
Summary: A MicroPython library for the Max7219 8x8 LED matrix driver
Home-page: https://github.com/enchant97/micropython-max7219
License: MIT
Keywords: micropython,max7219
Classifier: Development Status :: 4 - Beta
Classifier: Programming Language :: Python :: 3 :: Only
Classifier: Intended Audience :: Developers
Classifier: Programming Language :: Python :: Implementation :: MicroPython
Classifier: License :: OSI Approved :: MIT License
License-File: LICENSE.txt
